{
  "AC Unit": {
    "displayName": "AC Unit",
    "actions": [
      "Inspect",
      "Use With..."
    ],
    "story": "Original Story"
  },
  "Airvent ArtRoom": {
    "displayName": "Air Vent",
    "actions": [
      "Open",
      "Close"
    ],
    "story": "Original Story"
  },
  "Airvent DiningRoom": {
    "displayName": "Air Vent",
    "actions": [
      "Open",
      "Close"
    ],
    "story": "Original Story"
  },
  "Airvent DownstairsGuestBathroom": {
    "displayName": "Air Vent",
    "actions": [
      "Open",
      "Close"
    ],
    "story": "Original Story"
  },
  "Airvent GarageWall": {
    "displayName": "Air Vent",
    "actions": [
      "Inspect",
      "Use With..."
    ],
    "story": "Original Story"
  },
  "Airvent Kitchen": {
    "displayName": "Air Vent",
    "actions": [
      "Open",
      "Close"
    ],
    "story": "Original Story"
  },
  "Airvent LaundryRoom": {
    "displayName": "Air Vent",
    "actions": [
      "Open",
      "Close"
    ],
    "story": "Original Story"
  },
  "Airvent LivingRoom": {
    "displayName": "Air Vent",
    "actions": [
      "Open",
      "Close"
    ],
    "story": "Original Story"
  },
  "Airvent MasterBathroom": {
    "displayName": "Air Vent",
    "actions": [
      "Open",
      "Close"
    ],
    "story": "Original Story"
  },
  "Airvent MasterBedroom": {
    "displayName": "Air Vent",
    "actions": [
      "Open",
      "Close"
    ],
    "story": "Original Story"
  },
  "Airvent SpareRoom": {
    "displayName": "Air Vent",
    "actions": [
      "Open",
      "Close"
    ],
    "story": "Original Story"
  },
  "Airvent Study": {
    "displayName": "Air Vent",
    "actions": [
      "Open",
      "Close"
    ],
    "story": "Original Story"
  },
  "Airvent UpstairsGuestBathroom": {
    "displayName": "Air Vent",
    "actions": [
      "Open",
      "Close"
    ],
    "story": "Original Story"
  },
  "Amala": {
    "displayName": "Amala",
    "actions": [
      "Inspect",
      "Talk",
      "Give"
    ],
    "story": "Original Story"
  },
  "Amy": {
    "displayName": "Amy",
    "actions": [
      "Inspect",
      "Talk",
      "Give",
      "Sex Radial",
      "Default Radial",
      "Missionary",
      "Doggy",
      "Cowgirl",
      "Against Wall",
      "Against Wall;New Position",
      "Scissor",
      "Finger Her",
      "Get Fingered"
    ],
    "story": "Original Story"
  },
  "Arin": {
    "displayName": "Arin",
    "actions": [
      "Inspect",
      "Talk",
      "Give"
    ],
    "story": "Original Story"
  },
  "Armchair": {
    "displayName": "Armchair",
    "actions": [
      "Sit"
    ],
    "story": "A Vickie Vixen Valentine"
  },
  "ArtRoomWindow": {
    "displayName": "Window",
    "actions": [
      "Inspect",
      "Use With...",
      "Lock"
    ],
    "story": "Original Story"
  },
  "Ashley": {
    "displayName": "Ashley",
    "actions": [],
    "story": "A Vickie Vixen Valentine"
  },
  "Ashley's Panties": {
    "displayName": "Ashley's Panties",
    "actions": [
      "Inspect",
      "Use With..."
    ],
    "story": "Original Story"
  },
  "AshleyTop": {
    "displayName": "Ashley's Top",
    "actions": [
      "Inspect",
      "Untie",
      "Secure"
    ],
    "story": "Original Story"
  },
  "Auxiliary Dock": {
    "displayName": "Media Dock",
    "actions": [
      "Inspect",
      "Use With..."
    ],
    "story": "Original Story"
  },
  "Bab's Special": {
    "displayName": "The Babs Special",
    "actions": [
      "Inspect",
      "Take",
      "Use With...",
      "Drink"
    ],
    "story": "Original Story"
  },
  "Babs": {
    "displayName": "Babs",
    "actions": [
      "Inspect",
      "Talk",
      "Give"
    ],
    "story": "Original Story"
  },
  "Bag of Money": {
    "displayName": "Bag of Money",
    "actions": [
      "Inspect",
      "Take",
      "Use With..."
    ],
    "story": "Original Story"
  },
  "Bathroom Door": {
    "displayName": "Bathroom Door",
    "actions": [
      "Open",
      "Close",
      "Lock"
    ],
    "story": "A Vickie Vixen Valentine"
  },
  "Battery Pack": {
    "displayName": "Battery Pack",
    "actions": [
      "Inspect",
      "Take",
      "Use With..."
    ],
    "story": "Original Story"
  },
  "Bed (Left)": {
    "displayName": "Bed (Left)",
    "actions": [
      "Lay Down",
      "Check Underneath"
    ],
    "story": "A Vickie Vixen Valentine"
  },
  "Bed (Right)": {
    "displayName": "Bed (Right)",
    "actions": [
      "Lay Down",
      "Check Underneath"
    ],
    "story": "A Vickie Vixen Valentine"
  },
  "Bedroom Closet Door (Left)": {
    "displayName": "Bedroom Closet Door (Left)",
    "actions": [
      "Open"
    ],
    "story": "A Vickie Vixen Valentine"
  },
  "Bedroom Closet Door (Right)": {
    "displayName": "Bedroom Closet Door (Right)",
    "actions": [
      "Open"
    ],
    "story": "A Vickie Vixen Valentine"
  },
  "Bedroom Door": {
    "displayName": "Bedroom Door",
    "actions": [
      "Open",
      "Close"
    ],
    "story": "A Vickie Vixen Valentine"
  },
  "Bedsheet1": {
    "displayName": "Stained Bedsheet",
    "actions": [
      "Inspect",
      "Take",
      "Use With...",
      "Wear Bedsheet"
    ],
    "story": "Original Story"
  },
  "Bedsheet2": {
    "displayName": "Stained Bedsheet",
    "actions": [
      "Inspect",
      "Take",
      "Use With...",
      "Wear Bedsheet"
    ],
    "story": "Original Story"
  },
  "Bedsheet3": {
    "displayName": "Stained Bedsheet",
    "actions": [
      "Inspect",
      "Take",
      "Use With...",
      "Wear Bedsheet"
    ],
    "story": "Original Story"
  },
  "Bedsheet4": {
    "displayName": "Stained Bedsheet",
    "actions": [
      "Inspect",
      "Take",
      "Use With...",
      "Wear Bedsheet"
    ],
    "story": "Original Story"
  },
  "Bedsheet5": {
    "displayName": "Stained Bedsheet",
    "actions": [
      "Inspect",
      "Take",
      "Use With...",
      "Wear Bedsheet"
    ],
    "story": "Original Story"
  },
  "BikeLock": {
    "displayName": "Bike Lock",
    "actions": [
      "Inspect",
      "Punch",
      "Use With..."
    ],
    "story": "Original Story"
  },
  "BikeLockKey": {
    "displayName": "Tiny Key",
    "actions": [
      "Inspect",
      "Take",
      "Use With..."
    ],
    "story": "Original Story"
  },
  "Blue Hair Dye": {
    "displayName": "Blue Hair Dye",
    "actions": [
      "Inspect",
      "Take",
      "Use With..."
    ],
    "story": "Original Story"
  },
  "Blueprints": {
    "displayName": "Blueprints",
    "actions": [
      "Inspect",
      "Take",
      "Use With..."
    ],
    "story": "Original Story"
  },
  "Box of Nails": {
    "displayName": "Box of Nails",
    "actions": [
      "Inspect",
      "Take",
      "Use With..."
    ],
    "story": "Original Story"
  },
  "Breaker Panel": {
    "displayName": "Breaker Panel",
    "actions": [
      "Inspect",
      "Use With...",
      "Reset Breaker"
    ],
    "story": "Original Story"
  },
  "Briefcase": {
    "displayName": "Briefcase",
    "actions": [
      "Inspect",
      "Take",
      "Use With..."
    ],
    "story": "Original Story"
  },
  "Brittney": {
    "displayName": "Brittney",
    "actions": [
      "Talk",
      "Give",
      "Oogle",
      "Brash Compliment",
      "Safe Compliment",
      "Listen",
      "Lean In",
      "Lean In ",
      "Motorboat",
      "Lay Down",
      "Top Off",
      "Lean Close",
      "Lean Close ",
      "Joke: Foul",
      "Joke: Off-Color",
      "Listen ",
      "Lean Close  ",
      "Gift",
      "Plan",
      "Give ",
      "Ask",
      "Approach",
      "Inquire",
      "Missionary",
      "Go Down On",
      "Doggy",
      "Cowgirl",
      "Plan  ",
      "Approach ",
      "Eat Out",
      "Get Head"
    ],
    "story": "Date Night With Brittney"
  },
  "Broom": {
    "displayName": "Broom",
    "actions": [
      "Inspect",
      "Use With...",
      "Take"
    ],
    "story": "Original Story"
  },
  "Bug Zapper": {
    "displayName": "Bug Zapper",
    "actions": [
      "Inspect",
      "Use With..."
    ],
    "story": "Original Story"
  },
  "Cabernet": {
    "displayName": "Cabernet",
    "actions": [
      "Inspect",
      "Drink",
      "Take"
    ],
    "story": "Original Story"
  },
  "CabinetLeft": {
    "displayName": "Cabinet",
    "actions": [
      "Open",
      "Close"
    ],
    "story": "A Vickie Vixen Valentine"
  },
  "CabinetRight": {
    "displayName": "Cabinet",
    "actions": [
      "Open",
      "Close"
    ],
    "story": "A Vickie Vixen Valentine"
  },
  "Camera": {
    "displayName": "Camera",
    "actions": [
      "Inspect",
      "Take",
      "Use With...",
      "Take Photo",
      "View Photos"
    ],
    "story": "Original Story"
  },
  "CatPicture": {
    "displayName": "Cat Picture",
    "actions": [
      "Inspect",
      "Move Aside"
    ],
    "story": "Original Story"
  },
  "Cell Phone Jammer": {
    "displayName": "Cell Phone Jammer",
    "actions": [
      "Inspect",
      "Use With..."
    ],
    "story": "Date Night With Brittney"
  },
  "Chardonnay": {
    "displayName": "Chardonnay",
    "actions": [
      "Inspect",
      "Drink"
    ],
    "story": "Original Story"
  },
  "Chicken": {
    "displayName": "Chicken",
    "actions": [
      "Inspect",
      "Use With...",
      "Take"
    ],
    "story": "Original Story"
  },
  "Chicken Nuggets": {
    "displayName": "Chicken Nuggets",
    "actions": [
      "Inspect",
      "Use With...",
      "Take",
      "Eat"
    ],
    "story": "Original Story"
  },
  "Chili Peppers": {
    "displayName": "Mama Chupacabra's",
    "actions": [
      "Inspect",
      "Take",
      "Use With..."
    ],
    "story": "Original Story"
  },
  "Choclate Syrup": {
    "displayName": "Chocolate Syrup",
    "actions": [
      "Inspect",
      "Use With...",
      "Take"
    ],
    "story": "Original Story"
  },
  "ChocolateBar": {
    "displayName": "Cannabis Chocolate",
    "actions": [
      "Inspect"
    ],
    "story": "A Vickie Vixen Valentine"
  },
  "Clear Eyes": {
    "displayName": "Laxatives",
    "actions": [
      "Inspect",
      "Take",
      "Use With..."
    ],
    "story": "Original Story"
  },
  "Closed Briefcase": {
    "displayName": "Closed Briefcase",
    "actions": [
      "Inspect",
      "Use With...",
      "Throw Dildo",
      "Unlock",
      "Tap",
      "Investigate;Music"
    ],
    "story": "Original Story"
  },
  "Clothes": {
    "displayName": "Ashley's Clothes",
    "actions": [
      "Inspect",
      "Take",
      "Use With..."
    ],
    "story": "Original Story"
  },
  "Clothesline Back": {
    "displayName": "Clothesline",
    "actions": [
      "Inspect",
      "Take Bedsheet"
    ],
    "story": "Original Story"
  },
  "Clothesline Front": {
    "displayName": "Clothesline",
    "actions": [
      "Inspect",
      "Take Bedsheet"
    ],
    "story": "Original Story"
  },
  "Coffee": {
    "displayName": "Coffee",
    "actions": [
      "Inspect",
      "Take",
      "Use With...",
      "Drink"
    ],
    "story": "Original Story"
  },
  "CollarBloody": {
    "displayName": "Collar",
    "actions": [
      "Inspect",
      "Take",
      "Use With..."
    ],
    "story": "Original Story"
  },
  "Compubrah": {
    "displayName": "Compubrah",
    "actions": [],
    "story": "Original Story"
  },
  "Compubrah BGC Handler": {
    "displayName": "Compubrah",
    "actions": [],
    "story": "Original Story"
  },
  "CompubrahTree": {
    "displayName": "Tree",
    "actions": [
      "Use With...",
      "Kick"
    ],
    "story": "Original Story"
  },
  "Computer": {
    "displayName": "Computer",
    "actions": [
      "Inspect",
      "Dating Profile",
      "Search Patrick"
    ],
    "story": "Date Night With Brittney"
  },
  "Condom": {
    "displayName": "Condom",
    "actions": [
      "Inspect",
      "Take",
      "Use With..."
    ],
    "story": "Original Story"
  },
  "Couch (Left)": {
    "displayName": "Couch (Left)",
    "actions": [
      "Sit"
    ],
    "story": "A Vickie Vixen Valentine"
  },
  "Couch (Middle)": {
    "displayName": "Couch (Middle)",
    "actions": [
      "Sit"
    ],
    "story": "A Vickie Vixen Valentine"
  },
  "Couch (Right)": {
    "displayName": "Couch (Right)",
    "actions": [
      "Sit"
    ],
    "story": "A Vickie Vixen Valentine"
  },
  "Cowboy Scorpiosmus": {
    "displayName": "Stingy Pinchy Boi",
    "actions": [
      "Inspect",
      "Take",
      "Use With..."
    ],
    "story": "Original Story"
  },
  "Credit Card": {
    "displayName": "Credit Card",
    "actions": [
      "Inspect",
      "Take",
      "Use With..."
    ],
    "story": "Original Story"
  },
  "Cucumber": {
    "displayName": "Cucumber",
    "actions": [
      "Inspect",
      "Take",
      "Use With...",
      "Eat"
    ],
    "story": "Original Story"
  },
  "DLiciousOutfit": {
    "displayName": "Weird Dinosaur Suit",
    "actions": [
      "Inspect",
      "Take",
      "Use With..."
    ],
    "story": "Original Story"
  },
  "DVD2": {
    "displayName": "\"The Uncertain\" DVD",
    "actions": [
      "Read Cover",
      "Take",
      "Open"
    ],
    "story": "A Vickie Vixen Valentine"
  },
  "Dan": {
    "displayName": "Dan",
    "actions": [
      "Inspect",
      "Talk",
      "Give"
    ],
    "story": "Original Story"
  },
  "Dark Long Sleeve Women's Top": {
    "displayName": "Dark Long Sleeve Women's Top",
    "actions": [
      "Inspect",
      "Take",
      "Use With..."
    ],
    "story": "Original Story"
  },
  "DeadSnake": {
    "displayName": "Dead Snake",
    "actions": [
      "Inspect",
      "Take"
    ],
    "story": "Original Story"
  },
  "Derek": {
    "displayName": "Derek",
    "actions": [
      "Inspect",
      "Talk",
      "Give",
      "Missionary (Swap)",
      "Doggy (Swap)",
      "Sex Radial",
      "Default;Radial",
      "Against Wall (Swap)",
      "Cowboy (Swap)",
      "Poke",
      "Loot",
      "Poke;Chest",
      "Poke;Ass",
      "Cowboy"
    ],
    "story": "Original Story"
  },
  "Derek's Shirt": {
    "displayName": "Derek's Shirt",
    "actions": [
      "Inspect",
      "Use With..."
    ],
    "story": "Original Story"
  },
  "Desk Drawer Left": {
    "displayName": "Drawer",
    "actions": [
      "Open",
      "Close"
    ],
    "story": "A Vickie Vixen Valentine"
  },
  "Desk Drawer Right": {
    "displayName": "Drawer",
    "actions": [
      "Open",
      "Close"
    ],
    "story": "A Vickie Vixen Valentine"
  },
  "Diary": {
    "displayName": "Madison's Diary",
    "actions": [
      "Inspect",
      "Take",
      "Use With...",
      "Read"
    ],
    "story": "Original Story"
  },
  "Dining Chair": {
    "displayName": "Dining Chair",
    "actions": [
      "Sit"
    ],
    "story": "A Vickie Vixen Valentine"
  },
  "Dining Chair 2": {
    "displayName": "Dining Chair 2",
    "actions": [
      "Sit"
    ],
    "story": "A Vickie Vixen Valentine"
  },
  "DirtMound": {
    "displayName": "Mound of Dirt",
    "actions": [
      "Inspect"
    ],
    "story": "A Vickie Vixen Valentine"
  },
  "DirtyClue1": {
    "displayName": "Clue #1",
    "actions": [
      "Inspect",
      "Take",
      "Use With..."
    ],
    "story": "Original Story"
  },
  "DirtyClue2": {
    "displayName": "Clue #2",
    "actions": [
      "Inspect",
      "Take",
      "Use With..."
    ],
    "story": "Original Story"
  },
  "DirtyClue3": {
    "displayName": "Clue #3",
    "actions": [
      "Inspect",
      "Take",
      "Use With..."
    ],
    "story": "Original Story"
  },
  "Discarded Magazine": {
    "displayName": "Discarded Magazine",
    "actions": [
      "Inspect",
      "Take",
      "Use With..."
    ],
    "story": "Original Story"
  },
  "Disembodied Head": {
    "displayName": "Patrick's Head",
    "actions": [
      "Inspect",
      "Take",
      "Use With...",
      "Hold",
      "Put Away"
    ],
    "story": "Original Story"
  },
  "Doja Cat": {
    "displayName": "Doja Cat",
    "actions": [
      "Inspect",
      "Talk",
      "Give"
    ],
    "story": "Original Story"
  },
  "Double-Sided Dildo": {
    "displayName": "A Dildo",
    "actions": [
      "Inspect",
      "Take",
      "Use With...",
      "Hold in Hand"
    ],
    "story": "Original Story"
  },
  "DownstairsToilet": {
    "displayName": "Open Toilet",
    "actions": [
      "Sit",
      "Drink From",
      "Look At"
    ],
    "story": "Original Story"
  },
  "Dresser": {
    "displayName": "Dresser",
    "actions": [
      "Inspect",
      "Use With..."
    ],
    "story": "Original Story"
  },
  "Drone": {
    "displayName": "Drone",
    "actions": [
      "Inspect",
      "Take",
      "Use With..."
    ],
    "story": "Original Story"
  },
  "Dryer": {
    "displayName": "Dryer",
    "actions": [
      "Inspect",
      "Open",
      "Use With..."
    ],
    "story": "Original Story"
  },
  "Dryer Door": {
    "displayName": "Dryer Door",
    "actions": [
      "Open",
      "Close",
      "Use With..."
    ],
    "story": "Original Story"
  },
  "DryerSeat": {
    "displayName": "Dryer Seat",
    "actions": [
      "Hop Up",
      "Sit"
    ],
    "story": "Original Story"
  },
  "Duct Tape": {
    "displayName": "Duct Tape",
    "actions": [
      "Inspect",
      "Take",
      "Use With..."
    ],
    "story": "Original Story"
  },
  "E-Cig Vape": {
    "displayName": "Vape",
    "actions": [
      "Inspect",
      "Use With...",
      "Blaze",
      "Take"
    ],
    "story": "Original Story"
  },
  "Eggs": {
    "displayName": "Eggs",
    "actions": [
      "Inspect",
      "Use With...",
      "Take"
    ],
    "story": "Original Story"
  },
  "Empty Cup": {
    "displayName": "Empty Cup",
    "actions": [
      "Inspect",
      "Use With..."
    ],
    "story": "Original Story"
  },
  "EtherealClue": {
    "displayName": "Clue #5",
    "actions": [
      "Inspect",
      "Take",
      "Use With..."
    ],
    "story": "Original Story"
  },
  "Face Cream": {
    "displayName": "Spermicidal Lube",
    "actions": [
      "Inspect"
    ],
    "story": "Date Night With Brittney"
  },
  "Faucet": {
    "displayName": "Faucet",
    "actions": [
      "Inspect",
      "Use With...",
      "Drink"
    ],
    "story": "Original Story"
  },
  "Fifty Dollars": {
    "displayName": "Fifty Dollars",
    "actions": [
      "Inspect",
      "Take",
      "Use With..."
    ],
    "story": "Original Story"
  },
  "Film Camera": {
    "displayName": "Film Camera",
    "actions": [
      "Inspect",
      "Take",
      "Use With..."
    ],
    "story": "Original Story"
  },
  "Fire Pit": {
    "displayName": "Fire Pit",
    "actions": [
      "Inspect"
    ],
    "story": "A Vickie Vixen Valentine"
  },
  "Fireplace": {
    "displayName": "Fireplace",
    "actions": [
      "Inspect",
      "Use With...",
      "Roast the Head",
      "Grab the Head"
    ],
    "story": "Original Story"
  },
  "Flask": {
    "displayName": "Flask",
    "actions": [
      "Inspect",
      "Drink",
      "Hold in Hand",
      "Shake"
    ],
    "story": "Original Story"
  },
  "Flower": {
    "displayName": "Flower",
    "actions": [
      "Inspect",
      "Pick "
    ],
    "story": "Date Night With Brittney"
  },
  "Foam Finger": {
    "displayName": "Foam Finger",
    "actions": [
      "Inspect",
      "Take",
      "Use With..."
    ],
    "story": "Original Story"
  },
  "Forest HotTub Seat 1": {
    "displayName": "Hot Tub Seat",
    "actions": [
      "Sit"
    ],
    "story": "Original Story"
  },
  "Forest HotTub Seat 2": {
    "displayName": "Hot Tub Seat",
    "actions": [
      "Sit"
    ],
    "story": "Original Story"
  },
  "Forest HotTub Seat 3": {
    "displayName": "Hot Tub Seat",
    "actions": [
      "Sit"
    ],
    "story": "Original Story"
  },
  "Forest HotTub Seat 4": {
    "displayName": "Hot Tub Seat",
    "actions": [
      "Sit"
    ],
    "story": "Original Story"
  },
  "Frank": {
    "displayName": "Frank",
    "actions": [
      "Inspect",
      "Talk",
      "Give",
      "Slap Awake",
      "Loot",
      "Sex Radial",
      "Default Radial",
      "Doggy (Swap)",
      "Missionary (Swap)",
      "Cowboy (Swap)",
      "Against Wall (Swap)",
      "Cowboy"
    ],
    "story": "Original Story"
  },
  "Frank's Chair": {
    "displayName": "Comfy Chair",
    "actions": [
      "Sit",
      "Inspect"
    ],
    "story": "Date Night With Brittney"
  },
  "Freezer": {
    "displayName": "Freezer",
    "actions": [
      "Open",
      "Close",
      "Inspect",
      "Use With..."
    ],
    "story": "Original Story"
  },
  "Fridge": {
    "displayName": "Fridge",
    "actions": [
      "Open",
      "Close"
    ],
    "story": "A Vickie Vixen Valentine"
  },
  "Front Door": {
    "displayName": "Front Door",
    "actions": [
      "Open",
      "Shoo the Stranger Away"
    ],
    "story": "Original Story"
  },
  "Garage Door": {
    "displayName": "Garage Door",
    "actions": [
      "Open",
      "Close"
    ],
    "story": "A Vickie Vixen Valentine"
  },
  "GarageBinMovable": {
    "displayName": "Bin",
    "actions": [
      "Inspect",
      "Move Aside"
    ],
    "story": "Original Story"
  },
  "GarageWallAirVent": {
    "displayName": "Garage Air Vent",
    "actions": [
      "Inspect",
      "Use With..."
    ],
    "story": "Original Story"
  },
  "Gastronomy Book": {
    "displayName": "Gastronomy Book",
    "actions": [
      "Inspect",
      "Use With...",
      "Take"
    ],
    "story": "Original Story"
  },
  "GazeboFuseBox": {
    "displayName": "Gazebo Fuse Box",
    "actions": [
      "Inspect",
      "Reset Fuse",
      "Use With..."
    ],
    "story": "Original Story"
  },
  "Gisella": {
    "displayName": "Gisella",
    "actions": [
      "Inspect",
      "Talk",
      "Give",
      "Untie"
    ],
    "story": "Original Story"
  },
  "Gisella's Trailer": {
    "displayName": "Gisella's Trailer",
    "actions": [
      "Inspect",
      "Knock"
    ],
    "story": "Original Story"
  },
  "Glasses": {
    "displayName": "Glasses",
    "actions": [
      "Inspect",
      "Take",
      "Use With..."
    ],
    "story": "Original Story"
  },
  "GlowingMushroom1": {
    "displayName": "Brahroot",
    "actions": [
      "Inspect",
      "Take",
      "Use With..."
    ],
    "story": "Original Story"
  },
  "GlowingMushroom2": {
    "displayName": "Brahroot",
    "actions": [
      "Inspect",
      "Take",
      "Use With..."
    ],
    "story": "Original Story"
  },
  "GlowingMushroom3": {
    "displayName": "Brahroot",
    "actions": [
      "Inspect",
      "Take",
      "Use With..."
    ],
    "story": "Original Story"
  },
  "GlowingMushroom4": {
    "displayName": "Brahroot",
    "actions": [
      "Inspect",
      "Take",
      "Use With..."
    ],
    "story": "Original Story"
  },
  "GlowingMushroom5": {
    "displayName": "Brahroot",
    "actions": [
      "Inspect",
      "Take",
      "Use With..."
    ],
    "story": "Original Story"
  },
  "Gut Grip": {
    "displayName": "Gut Grip",
    "actions": [
      "Inspect",
      "Use With...",
      "Ingest"
    ],
    "story": "Date Night With Brittney"
  },
  "Gutter": {
    "displayName": "Gutter",
    "actions": [
      "Climb",
      "Inspect"
    ],
    "story": "A Vickie Vixen Valentine"
  },
  "Hammer": {
    "displayName": "Hammer",
    "actions": [
      "Inspect",
      "Take",
      "Use With..."
    ],
    "story": "Original Story"
  },
  "Hammer2": {
    "displayName": "Murderer's Hammer",
    "actions": [
      "Inspect",
      "Take",
      "Use With..."
    ],
    "story": "Original Story"
  },
  "Hidden Compartment": {
    "displayName": "Hidden Compartment",
    "actions": [
      "Inspect",
      "Open",
      "Close"
    ],
    "story": "Original Story"
  },
  "HoleInFence": {
    "displayName": "Suspicious Hole",
    "actions": [
      "Inspect",
      "Peek Into"
    ],
    "story": "Original Story"
  },
  "Hot Tub Base": {
    "displayName": "Hot Tub",
    "actions": [
      "Inspect",
      "Use With..."
    ],
    "story": "Original Story"
  },
  "Hot Tub Drink Tray": {
    "displayName": "Hot Tub Drink Tray",
    "actions": [
      "Inspect",
      "Use With..."
    ],
    "story": "Original Story"
  },
  "Hot Tub Drink Tray Forest": {
    "displayName": "Hot Tub Drink Tray",
    "actions": [
      "Inspect",
      "Use With..."
    ],
    "story": "Original Story"
  },
  "Hot Tub Stairs": {
    "displayName": "Hot Tub Stairs",
    "actions": [
      "Get Out"
    ],
    "story": "A Vickie Vixen Valentine"
  },
  "HotTub Seat 1": {
    "displayName": "Hot Tub Seat",
    "actions": [
      "Sit"
    ],
    "story": "Original Story"
  },
  "HotTub Seat 2": {
    "displayName": "Hot Tub Seat",
    "actions": [
      "Sit"
    ],
    "story": "Original Story"
  },
  "HotTub Seat 3": {
    "displayName": "Hot Tub Seat",
    "actions": [
      "Sit"
    ],
    "story": "Original Story"
  },
  "HotTub Seat 4": {
    "displayName": "Hot Tub Seat",
    "actions": [
      "Sit"
    ],
    "story": "Original Story"
  },
  "HotTubCoverFolded": {
    "displayName": "Hot Tub Cover",
    "actions": [
      "Inspect",
      "Take",
      "Use With..."
    ],
    "story": "Original Story"
  },
  "HotTubCoverUnfolded": {
    "displayName": "Hot Tub Cover Stage",
    "actions": [
      "Inspect",
      "Take",
      "Use With..."
    ],
    "story": "Original Story"
  },
  "Jack Daniel's": {
    "displayName": "Whack Spaniels",
    "actions": [
      "Inspect",
      "Take",
      "Use With..."
    ],
    "story": "Date Night With Brittney"
  },
  "Joint": {
    "displayName": "Joint",
    "actions": [
      "Inspect",
      "Take",
      "Use With..."
    ],
    "story": "Original Story"
  },
  "Jukebox": {
    "displayName": "Jukebox",
    "actions": [
      "Inspect",
      "Use With...",
      "Tag With;Nano-Nuts"
    ],
    "story": "Original Story"
  },
  "Katana": {
    "displayName": "Katana",
    "actions": [
      "Inspect",
      "Use With...",
      "Punch"
    ],
    "story": "Original Story"
  },
  "Katherine": {
    "displayName": "Katherine",
    "actions": [
      "Inspect",
      "Talk",
      "Give",
      "Fuck",
      "Sex Radial",
      "Default Radial",
      "Pose Radial",
      "Lay Down",
      "Hands;Behind Head",
      "Kneel",
      "Hands;Behind Back",
      "Bend Over",
      "Take a Selfie",
      "Touch Herself",
      "No!",
      "No.",
      "Noo!",
      "...No?",
      "No-no-no!",
      "...No!",
      "N-n-no!",
      "Nnnooooo!",
      "...Brah?!",
      "Fuck;(POV)"
    ],
    "story": "Original Story"
  },
  "KatherinePhone": {
    "displayName": "Katherine's Phone",
    "actions": [
      "Inspect",
      "Take",
      "Use With..."
    ],
    "story": "A Vickie Vixen Valentine"
  },
  "Kettle": {
    "displayName": "Kettle",
    "actions": [
      "Inspect",
      "Use With...",
      "Take"
    ],
    "story": "Original Story"
  },
  "Key": {
    "displayName": "Stashbox Key",
    "actions": [
      "Inspect"
    ],
    "story": "A Vickie Vixen Valentine"
  },
  "Key2": {
    "displayName": "Brittney's Key",
    "actions": [
      "Inspect"
    ],
    "story": "Date Night With Brittney"
  },
  "Key3": {
    "displayName": "Trunk Key",
    "actions": [
      "Inspect",
      "Take",
      "Use With..."
    ],
    "story": "Original Story"
  },
  "Keychain": {
    "displayName": "Cock Keyring",
    "actions": [
      "Inspect",
      "Take",
      "Use With..."
    ],
    "story": "Original Story"
  },
  "KitchenCabinet5": {
    "displayName": "Cabinet",
    "actions": [
      "Open"
    ],
    "story": "A Vickie Vixen Valentine"
  },
  "KitchenCabinet6": {
    "displayName": "Cabinet",
    "actions": [
      "Open",
      "Close"
    ],
    "story": "Original Story"
  },
  "KitchenCabinet7": {
    "displayName": "Cabinet",
    "actions": [
      "Open",
      "Close"
    ],
    "story": "Original Story"
  },
  "KitchenCabinet8": {
    "displayName": "Cabinet",
    "actions": [
      "Open",
      "Close"
    ],
    "story": "Original Story"
  },
  "Knife": {
    "displayName": "Knife",
    "actions": [
      "Inspect",
      "Take",
      "Use With..."
    ],
    "story": "Original Story"
  },
  "LRTVBackButton": {
    "displayName": "Back",
    "actions": [
      "Select"
    ],
    "story": "Original Story"
  },
  "LRTVPlayAllButton": {
    "displayName": "Play All",
    "actions": [
      "Select"
    ],
    "story": "Original Story"
  },
  "LRTVSongFiveButton": {
    "displayName": "Loop Track 5",
    "actions": [
      "Select"
    ],
    "story": "Original Story"
  },
  "LRTVSongFourButton": {
    "displayName": "Loop Track 4",
    "actions": [
      "Select"
    ],
    "story": "Original Story"
  },
  "LRTVSongOneButton": {
    "displayName": "Loop Track 1",
    "actions": [
      "Select"
    ],
    "story": "Original Story"
  },
  "LRTVSongSixButton": {
    "displayName": "Loop Track 6",
    "actions": [
      "Select"
    ],
    "story": "Original Story"
  },
  "LRTVSongThreeButton": {
    "displayName": "Loop Track 3",
    "actions": [
      "Select"
    ],
    "story": "Original Story"
  },
  "LRTVSongTwoButton": {
    "displayName": "Loop Track 2",
    "actions": [
      "Select"
    ],
    "story": "Original Story"
  },
  "Laptop": {
    "displayName": "Laptop",
    "actions": [
      "Inspect",
      "Use With...",
      "Unlock",
      "Invite Lety",
      "Browse YouTool",
      "Sign Into YouTool",
      "Return to Desktop"
    ],
    "story": "Original Story"
  },
  "Laundry Room Door": {
    "displayName": "Laundry Room Door",
    "actions": [
      "Open",
      "Close"
    ],
    "story": "A Vickie Vixen Valentine"
  },
  "LawnChair1": {
    "displayName": "Lawn Chair",
    "actions": [
      "Sit"
    ],
    "story": "A Vickie Vixen Valentine"
  },
  "LawnChair2": {
    "displayName": "Lawn Chair",
    "actions": [
      "Sit"
    ],
    "story": "A Vickie Vixen Valentine"
  },
  "LawnChair3": {
    "displayName": "Lawn Chair",
    "actions": [
      "Sit"
    ],
    "story": "A Vickie Vixen Valentine"
  },
  "LawnChair4": {
    "displayName": "Lawn Chair",
    "actions": [
      "Sit"
    ],
    "story": "A Vickie Vixen Valentine"
  },
  "Leah": {
    "displayName": "Leah",
    "actions": [
      "Inspect",
      "Talk",
      "Give",
      "Sex Radial",
      "Default Radial",
      "Help",
      "Fuck",
      "Fuck;(POV)"
    ],
    "story": "Original Story"
  },
  "Lety": {
    "displayName": "Lety",
    "actions": [
      "Inspect",
      "Talk",
      "Give",
      "Fuck",
      "Doggy",
      "Missionary",
      "Sex Radial",
      "Default;Radial",
      "Cowgirl",
      "Sixty Nine",
      "Her",
      "Rachael",
      "Bang",
      "Against Wall",
      "Against Wall;New Position",
      "Fuck;(POV)",
      "Ridiculous;CutScene",
      "Poke;Chest",
      "Poke;Ass",
      "Scissor",
      "Finger Her",
      "Get Fingered"
    ],
    "story": "Original Story"
  },
  "LivingRoomTV": {
    "displayName": "Dining Room TV",
    "actions": [
      "Inspect",
      "Take",
      "Talk to;Compubrah"
    ],
    "story": "Original Story"
  },
  "Liz Katz": {
    "displayName": "Liz Katz",
    "actions": [
      "Inspect",
      "Talk",
      "Give",
      "Default;Radial",
      "Sex Radial",
      "Fuck",
      "Get Head",
      "Eat Out"
    ],
    "story": "Original Story"
  },
  "LizKatzButt": {
    "displayName": "Liz Katz's Butt",
    "actions": [
      "Inspect",
      "Spank",
      "Rub",
      "Grab Waist"
    ],
    "story": "Original Story"
  },
  "MP3 Player": {
    "displayName": "MP3 Player",
    "actions": [
      "Inspect",
      "Reach For",
      "Use With...",
      "Throw Dildo",
      "Take"
    ],
    "story": "Original Story"
  },
  "MP3 Player DC": {
    "displayName": "Doja Cat's MP3 Player",
    "actions": [
      "Inspect",
      "Take",
      "Use With..."
    ],
    "story": "Original Story"
  },
  "Madison": {
    "displayName": "Madison",
    "actions": [],
    "story": "A Vickie Vixen Valentine"
  },
  "Madison's Phone": {
    "displayName": "Your Phone",
    "actions": [
      "Check"
    ],
    "story": "A Vickie Vixen Valentine"
  },
  "Marijuana": {
    "displayName": "CatNip",
    "actions": [
      "Inspect",
      "Shake"
    ],
    "story": "A Vickie Vixen Valentine"
  },
  "Master Bathroom Door": {
    "displayName": "Master Bathroom Door",
    "actions": [
      "Open",
      "Close",
      "Lock"
    ],
    "story": "A Vickie Vixen Valentine"
  },
  "Master Bedroom Door": {
    "displayName": "Master Bedroom Door",
    "actions": [
      "Knock",
      "Close",
      "Open"
    ],
    "story": "A Vickie Vixen Valentine"
  },
  "Matchbox": {
    "displayName": "Matchbox",
    "actions": [
      "Inspect",
      "Take",
      "Use With..."
    ],
    "story": "Original Story"
  },
  "Mayonnaise": {
    "displayName": "Mayonnaise",
    "actions": [
      "Inspect",
      "Use With...",
      "Take"
    ],
    "story": "Original Story"
  },
  "Merlot": {
    "displayName": "Merlot",
    "actions": [
      "Inspect",
      "Take",
      "Drink"
    ],
    "story": "Original Story"
  },
  "Microwave": {
    "displayName": "Microwave",
    "actions": [
      "Inspect",
      "Take"
    ],
    "story": "Date Night With Brittney"
  },
  "Microwave Door": {
    "displayName": "Microwave Door",
    "actions": [
      "Open",
      "Close"
    ],
    "story": "Original Story"
  },
  "MistletoeBallsDecoration": {
    "displayName": "Nana's Special Mistletoe",
    "actions": [
      "Inspect",
      "Use With..."
    ],
    "story": "Original Story"
  },
  "Money Makers Monthly": {
    "displayName": "Money Makers Monthly",
    "actions": [
      "Inspect",
      "Use With...",
      "Peruse",
      "Take"
    ],
    "story": "Original Story"
  },
  "Motor Oil": {
    "displayName": "Michelin Motor Oil",
    "actions": [
      "Inspect",
      "Take",
      "Use With..."
    ],
    "story": "Date Night With Brittney"
  },
  "Mug": {
    "displayName": "Mug",
    "actions": [
      "Inspect",
      "Take",
      "Use With...",
      "Drink"
    ],
    "story": "Original Story"
  },
  "Murray's Radio": {
    "displayName": "Murray's Radio",
    "actions": [
      "Inspect",
      "Talk to Murray",
      "Try Radio"
    ],
    "story": "Original Story"
  },
  "Natty Lite 1": {
    "displayName": "Natty Lite",
    "actions": [
      "Inspect"
    ],
    "story": "Original Story"
  },
  "Natty Lite 10": {
    "displayName": "Natty Lite",
    "actions": [
      "Inspect",
      "Take"
    ],
    "story": "Original Story"
  },
  "Natty Lite 11": {
    "displayName": "Natty Lite",
    "actions": [
      "Inspect",
      "Take"
    ],
    "story": "Original Story"
  },
  "Natty Lite 12": {
    "displayName": "Natty Lite",
    "actions": [
      "Inspect",
      "Take"
    ],
    "story": "Original Story"
  },
  "Natty Lite 13": {
    "displayName": "Natty Lite",
    "actions": [
      "Inspect",
      "Take"
    ],
    "story": "Original Story"
  },
  "Natty Lite 14": {
    "displayName": "Natty Lite",
    "actions": [
      "Inspect",
      "Take"
    ],
    "story": "Original Story"
  },
  "Natty Lite 2": {
    "displayName": "Natty Lite",
    "actions": [
      "Inspect"
    ],
    "story": "Original Story"
  },
  "Natty Lite 3": {
    "displayName": "Natty Lite",
    "actions": [
      "Inspect"
    ],
    "story": "Original Story"
  },
  "Natty Lite 4": {
    "displayName": "Natty Lite",
    "actions": [
      "Inspect"
    ],
    "story": "Original Story"
  },
  "Natty Lite 5": {
    "displayName": "Natty Lite",
    "actions": [
      "Inspect"
    ],
    "story": "Original Story"
  },
  "Natty Lite 6": {
    "displayName": "Natty Lite",
    "actions": [
      "Inspect"
    ],
    "story": "Original Story"
  },
  "Natty Lite 7": {
    "displayName": "Natty Lite",
    "actions": [
      "Inspect",
      "Take"
    ],
    "story": "Original Story"
  },
  "Natty Lite 8": {
    "displayName": "Natty Lite",
    "actions": [
      "Inspect",
      "Take"
    ],
    "story": "Original Story"
  },
  "Natty Lite 9": {
    "displayName": "Natty Lite",
    "actions": [
      "Inspect",
      "Take"
    ],
    "story": "Original Story"
  },
  "Nighstand Drawer 1": {
    "displayName": "Nighstand Drawer 1",
    "actions": [
      "Open",
      "Close"
    ],
    "story": "A Vickie Vixen Valentine"
  },
  "Nightstand1": {
    "displayName": "Nightstand (L)",
    "actions": [
      "Open",
      "Close"
    ],
    "story": "Original Story"
  },
  "Nightstand2": {
    "displayName": "Nightstand (R)",
    "actions": [
      "Open",
      "Close"
    ],
    "story": "Original Story"
  },
  "Notebook": {
    "displayName": "Notebook",
    "actions": [
      "Inspect",
      "Take",
      "Use With...",
      "Hold"
    ],
    "story": "Original Story"
  },
  "Office Chair": {
    "displayName": "Office Chair",
    "actions": [
      "Sit"
    ],
    "story": "A Vickie Vixen Valentine"
  },
  "Office Drawer Left": {
    "displayName": "Drawer",
    "actions": [
      "Open",
      "Close"
    ],
    "story": "A Vickie Vixen Valentine"
  },
  "Office Drawer Right": {
    "displayName": "Drawer",
    "actions": [
      "Open",
      "Close"
    ],
    "story": "A Vickie Vixen Valentine"
  },
  "Old Air Raid Siren": {
    "displayName": "Old Air Raid Siren",
    "actions": [
      "Inspect",
      "Use With...",
      "Tag With;Nano-Nuts"
    ],
    "story": "Original Story"
  },
  "Open Briefcase": {
    "displayName": "Sticky Briefcase",
    "actions": [
      "Inspect",
      "Talk",
      "Poke Boob",
      "Help"
    ],
    "story": "Combat Training"
  },
  "OrangeBin1": {
    "displayName": " ",
    "actions": [
      "Inspect",
      "Use With..."
    ],
    "story": "A Vickie Vixen Valentine"
  },
  "Outdoor Toilet": {
    "displayName": "Outdoor Toilet",
    "actions": [
      "Inspect"
    ],
    "story": "Original Story"
  },
  "Outhouse Toilet": {
    "displayName": "Outhouse Toilet",
    "actions": [
      "Inspect"
    ],
    "story": "Original Story"
  },
  "Outside Sofa 1 Left": {
    "displayName": "Sofa",
    "actions": [
      "Sit"
    ],
    "story": "A Vickie Vixen Valentine"
  },
  "Outside Sofa 1 Middle": {
    "displayName": "Sofa",
    "actions": [
      "Sit"
    ],
    "story": "A Vickie Vixen Valentine"
  },
  "Outside Sofa 1 Right": {
    "displayName": "Sofa",
    "actions": [
      "Sit"
    ],
    "story": "A Vickie Vixen Valentine"
  },
  "Outside Sofa 2 Left": {
    "displayName": "Sofa",
    "actions": [
      "Sit"
    ],
    "story": "A Vickie Vixen Valentine"
  },
  "Outside Sofa 2 Middle": {
    "displayName": "Sofa",
    "actions": [
      "Sit"
    ],
    "story": "A Vickie Vixen Valentine"
  },
  "Outside Sofa 2 Right": {
    "displayName": "Sofa",
    "actions": [
      "Sit"
    ],
    "story": "A Vickie Vixen Valentine"
  },
  "OwlMask1": {
    "displayName": "Owl Mask",
    "actions": [
      "Inspect",
      "Take",
      "Use With..."
    ],
    "story": "Original Story"
  },
  "OwlMask2": {
    "displayName": "Owl Mask",
    "actions": [
      "Inspect",
      "Take",
      "Use With..."
    ],
    "story": "Original Story"
  },
  "OwlMask3": {
    "displayName": "Owl Mask",
    "actions": [
      "Inspect",
      "Take",
      "Use With..."
    ],
    "story": "Original Story"
  },
  "OwlPainting": {
    "displayName": "Painting and Easel",
    "actions": [
      "Inspect",
      "Use With..."
    ],
    "story": "Original Story"
  },
  "PaddockButton": {
    "displayName": "Paddock Button",
    "actions": [
      "Inspect",
      "Press the Button"
    ],
    "story": "Original Story"
  },
  "Painkillers": {
    "displayName": "Allergy Medication",
    "actions": [
      "Inspect",
      "Take",
      "Use With..."
    ],
    "story": "A Vickie Vixen Valentine"
  },
  "Pantry Door (Left)": {
    "displayName": "Pantry Door (Left)",
    "actions": [
      "Open",
      "Close"
    ],
    "story": "A Vickie Vixen Valentine"
  },
  "Pantry Door (Right)": {
    "displayName": "Pantry Door (Right)",
    "actions": [
      "Open",
      "Close"
    ],
    "story": "A Vickie Vixen Valentine"
  },
  "Paper": {
    "displayName": "Notes About Brittney",
    "actions": [
      "Inspect"
    ],
    "story": "Date Night With Brittney"
  },
  "Paper Bag": {
    "displayName": "Fast Food Bag",
    "actions": [
      "Inspect",
      "Take",
      "Use With..."
    ],
    "story": "Original Story"
  },
  "Paper Bag Crunched": {
    "displayName": "Paper Bag Crunched",
    "actions": [
      "Inspect",
      "Use With..."
    ],
    "story": "Original Story"
  },
  "Patio Armchair": {
    "displayName": "Patio Armchair",
    "actions": [
      "Sit"
    ],
    "story": "A Vickie Vixen Valentine"
  },
  "Patio Armchair 2": {
    "displayName": "Patio Armchair (R)",
    "actions": [
      "Sit"
    ],
    "story": "Original Story"
  },
  "Patrick": {
    "displayName": "Patrick",
    "actions": [
      "Inspect",
      "Talk",
      "Give"
    ],
    "story": "Date Night With Brittney"
  },
  "Pencil": {
    "displayName": "Pencil",
    "actions": [
      "Inspect"
    ],
    "story": "A Vickie Vixen Valentine"
  },
  "Penguin": {
    "displayName": "Dusty Penguin",
    "actions": [
      "Inspect",
      "Take",
      "Use With...",
      "Set Free",
      "...Insert",
      "Disassemble"
    ],
    "story": "Original Story"
  },
  "Petition": {
    "displayName": "Petition",
    "actions": [
      "Inspect",
      "Use With...",
      "Take"
    ],
    "story": "Original Story"
  },
  "Phone Call": {
    "displayName": "Man's Voice",
    "actions": [],
    "story": "Date Night With Brittney"
  },
  "Phone2": {
    "displayName": "Phone",
    "actions": [
      "Inspect"
    ],
    "story": "Date Night With Brittney"
  },
  "Phone3": {
    "displayName": "Phone3",
    "actions": [
      "Inspect",
      "Take",
      "Use With..."
    ],
    "story": "A Vickie Vixen Valentine"
  },
  "Phone4": {
    "displayName": "Ashley's Phone",
    "actions": [
      "Check Texts",
      "Take",
      "Check Reminders"
    ],
    "story": "A Vickie Vixen Valentine"
  },
  "PinkUnderwear": {
    "displayName": "Goodbye Kitty Underwear",
    "actions": [
      "Inspect",
      "Take",
      "Use With..."
    ],
    "story": "Original Story"
  },
  "Pizza Box": {
    "displayName": "Pizza Box",
    "actions": [
      "Inspect",
      "Eat More"
    ],
    "story": "Date Night With Brittney"
  },
  "PlankPileInYard": {
    "displayName": "Wood Planks",
    "actions": [
      "Inspect",
      "Take",
      "Use With..."
    ],
    "story": "Original Story"
  },
  "PlanksFortification": {
    "displayName": "Barricade",
    "actions": [
      "Inspect",
      "Use With..."
    ],
    "story": "Original Story"
  },
  "PlanksFortificationExtraNails": {
    "displayName": "PlanksFortificationExtraNails",
    "actions": [
      "Inspect"
    ],
    "story": "Original Story"
  },
  "Player": {
    "displayName": "You",
    "actions": [
      "Remove Shirt",
      "Remove Pants",
      "Remove Boxers",
      "Put On Boxers",
      "Put On Pants",
      "Put On Shirt",
      "Remove Shoes",
      "Put On Shoes"
    ],
    "story": "A Vickie Vixen Valentine"
  },
  "PlayerBeerPongPractice": {
    "displayName": "Practice!",
    "actions": [
      "Inspect",
      "Start",
      "Stop",
      "Help"
    ],
    "story": "Original Story"
  },
  "PlexiglassHotTub": {
    "displayName": "Plexiglass Stage",
    "actions": [
      "Inspect",
      "Take",
      "Use With..."
    ],
    "story": "Original Story"
  },
  "PlexiglassStacked": {
    "displayName": "Plexiglass",
    "actions": [
      "Inspect",
      "Take",
      "Use With..."
    ],
    "story": "Original Story"
  },
  "Police Car": {
    "displayName": "Police Car",
    "actions": [
      "Inspect",
      "Use With...",
      "Tag With;Nano-Nuts"
    ],
    "story": "Original Story"
  },
  "Popcorn": {
    "displayName": "Popcorn",
    "actions": [
      "Inspect",
      "Take",
      "Use With..."
    ],
    "story": "Original Story"
  },
  "PopperBox": {
    "displayName": "Wizbanger Poppers",
    "actions": [
      "Inspect",
      "Throw One"
    ],
    "story": "Original Story"
  },
  "Potatoes": {
    "displayName": "Potatoes",
    "actions": [
      "Inspect",
      "Use With...",
      "Take"
    ],
    "story": "Original Story"
  },
  "Pouf": {
    "displayName": "Pouf",
    "actions": [
      "Sit"
    ],
    "story": "A Vickie Vixen Valentine"
  },
  "PrintableClue": {
    "displayName": "Clue #4",
    "actions": [
      "Inspect",
      "Take",
      "Use With..."
    ],
    "story": "Original Story"
  },
  "Printer": {
    "displayName": "Printer",
    "actions": [
      "Inspect",
      "Use With...",
      "Print Petition"
    ],
    "story": "Original Story"
  },
  "Rachael": {
    "displayName": "Rachael",
    "actions": [
      "Inspect",
      "Talk",
      "Give",
      "Bang",
      "Lety",
      "Her",
      "Sex Radial",
      "Default Radial",
      "Fuck;(POV)",
      "Ridiculous;CutScene"
    ],
    "story": "Original Story"
  },
  "Remote Control": {
    "displayName": "TV Remote",
    "actions": [
      "Inspect",
      "Take",
      "Start Music",
      "Stop Music",
      "Prev Track",
      "Next Track",
      "Play All",
      "Loop Current"
    ],
    "story": "Original Story"
  },
  "RipppedWhalePoster": {
    "displayName": "Ripped Whale Poster",
    "actions": [
      "Inspect",
      "Use With..."
    ],
    "story": "Original Story"
  },
  "Router": {
    "displayName": "Router",
    "actions": [
      "Inspect",
      "Turn Off",
      "Turn On",
      "Use With..."
    ],
    "story": "Original Story"
  },
  "Rum": {
    "displayName": "Rum",
    "actions": [
      "Inspect",
      "Drink",
      "Take"
    ],
    "story": "Original Story"
  },
  "SD Card": {
    "displayName": "SD Card",
    "actions": [
      "Inspect",
      "Take",
      "Use With..."
    ],
    "story": "Original Story"
  },
  "SRClosetDoor1": {
    "displayName": "Closet Door (L)",
    "actions": [
      "Open",
      "Close"
    ],
    "story": "Original Story"
  },
  "SRClosetDoor2": {
    "displayName": "Closet Door (R)",
    "actions": [
      "Open",
      "Close"
    ],
    "story": "Original Story"
  },
  "SRClosetDoor3": {
    "displayName": "Closet Door (L)",
    "actions": [
      "Open",
      "Close",
      "Hide Inside"
    ],
    "story": "Original Story"
  },
  "SRClosetDoor4": {
    "displayName": "Closet Door (R)",
    "actions": [
      "Open",
      "Close",
      "Hide Inside"
    ],
    "story": "Original Story"
  },
  "Safe": {
    "displayName": "Safe",
    "actions": [
      "Open",
      "Close"
    ],
    "story": "Original Story"
  },
  "Salami": {
    "displayName": "Salami",
    "actions": [
      "Inspect",
      "Take",
      "Use With...",
      "Eat"
    ],
    "story": "Original Story"
  },
  "Salmon": {
    "displayName": "Salmon",
    "actions": [
      "Inspect",
      "Use With...",
      "Take",
      "Eat"
    ],
    "story": "Original Story"
  },
  "Satchel": {
    "displayName": "Satchel",
    "actions": [
      "Inspect",
      "Unpack"
    ],
    "story": "Original Story"
  },
  "Scorpion Tequila": {
    "displayName": "El Escorpion Mezcal",
    "actions": [
      "Inspect",
      "Drink",
      "Take"
    ],
    "story": "Original Story"
  },
  "Shake Light": {
    "displayName": "Shake Light",
    "actions": [
      "Inspect",
      "Take",
      "Turn On",
      "Turn Off",
      "Instructions",
      "Use With..."
    ],
    "story": "Original Story"
  },
  "SleepingMaskFolded": {
    "displayName": "Sleeping Mask",
    "actions": [
      "Inspect",
      "Take",
      "Use With..."
    ],
    "story": "Original Story"
  },
  "Slider Door": {
    "displayName": "Slider Door",
    "actions": [
      "Open",
      "Close",
      "Unlock"
    ],
    "story": "A Vickie Vixen Valentine"
  },
  "Small Spare Closet Door (L)": {
    "displayName": "Closet Door",
    "actions": [
      "Open",
      "Close"
    ],
    "story": "A Vickie Vixen Valentine"
  },
  "Small Spare Closet Door (R)": {
    "displayName": "Closet Door",
    "actions": [
      "Open",
      "Close",
      "Inspect"
    ],
    "story": "A Vickie Vixen Valentine"
  },
  "SnowballBucket": {
    "displayName": "Snowball Bucket",
    "actions": [
      "Inspect",
      "Take",
      "Grab Snowball"
    ],
    "story": "Original Story"
  },
  "Soda": {
    "displayName": "Soda",
    "actions": [
      "Inspect",
      "Take",
      "Use With...",
      "Drink"
    ],
    "story": "Original Story"
  },
  "Sofa (Left)": {
    "displayName": "Sofa (Left)",
    "actions": [
      "Sit"
    ],
    "story": "A Vickie Vixen Valentine"
  },
  "Sofa (Right)": {
    "displayName": "Sofa (Right)",
    "actions": [
      "Sit"
    ],
    "story": "A Vickie Vixen Valentine"
  },
  "Spare Room 2 Door": {
    "displayName": "Room Door",
    "actions": [
      "Open",
      "Close"
    ],
    "story": "A Vickie Vixen Valentine"
  },
  "Spare Room Chair": {
    "displayName": "Spare Room Chair",
    "actions": [
      "Sit"
    ],
    "story": "A Vickie Vixen Valentine"
  },
  "Spare Room Door": {
    "displayName": "Spare Room Door",
    "actions": [
      "Open",
      "Close"
    ],
    "story": "A Vickie Vixen Valentine"
  },
  "SpareRoomSofaLeft": {
    "displayName": "Spare Room Sofa (L)",
    "actions": [
      "Sit"
    ],
    "story": "Original Story"
  },
  "SpareRoomSofaMiddle": {
    "displayName": "Sofa",
    "actions": [
      "Sit"
    ],
    "story": "A Vickie Vixen Valentine"
  },
  "SpareRoomSofaRight": {
    "displayName": "Spare Room Sofa (R)",
    "actions": [
      "Sit"
    ],
    "story": "Original Story"
  },
  "Speaker1": {
    "displayName": "Speaker with Sexy Beats",
    "actions": [
      "Inspect",
      "Turn Off",
      "Turn On"
    ],
    "story": "Date Night With Brittney"
  },
  "Speaker2": {
    "displayName": "Speaker",
    "actions": [
      "Inspect",
      "Use With...",
      "Take",
      "Turn On",
      "Turn Off",
      "Dance",
      "Dance...;Betterer"
    ],
    "story": "Original Story"
  },
  "Spoon": {
    "displayName": "Spoon",
    "actions": [
      "Inspect",
      "Take",
      "Use With..."
    ],
    "story": "Original Story"
  },
  "SprayPaintCan": {
    "displayName": "Spray Paint",
    "actions": [
      "Inspect",
      "Take",
      "Use With..."
    ],
    "story": "Original Story"
  },
  "StarbombBox": {
    "displayName": "Starbomb Box",
    "actions": [
      "Inspect",
      "Take",
      "Use With...",
      "Throw One"
    ],
    "story": "Original Story"
  },
  "Stephanie": {
    "displayName": "Stephanie",
    "actions": [
      "Inspect",
      "Talk",
      "Give",
      "Fuck",
      "Take Bag",
      "Panties Off",
      "Doggy",
      "Cowgirl",
      "Against Wall",
      "Missionary",
      "Sex Radial",
      "Default Radial",
      "Loot",
      "Scissor",
      "Finger Her",
      "Get Fingered"
    ],
    "story": "Original Story"
  },
  "Stepstool": {
    "displayName": "Step Stool",
    "actions": [
      "Inspect",
      "Take",
      "Use With..."
    ],
    "story": "Original Story"
  },
  "Stove": {
    "displayName": "Smelly Stove",
    "actions": [
      "Inspect",
      "Commit",
      "Sabotage"
    ],
    "story": "Date Night With Brittney"
  },
  "Study Closet Door (L)": {
    "displayName": "Closet Door",
    "actions": [
      "Open",
      "Close"
    ],
    "story": "A Vickie Vixen Valentine"
  },
  "Study Closet Door (R)": {
    "displayName": "Closet Door",
    "actions": [
      "Open",
      "Close"
    ],
    "story": "A Vickie Vixen Valentine"
  },
  "Study Door": {
    "displayName": "Study Door",
    "actions": [
      "Open",
      "Close"
    ],
    "story": "A Vickie Vixen Valentine"
  },
  "Sundress": {
    "displayName": "Sundress",
    "actions": [
      "Inspect",
      "Take",
      "Use With..."
    ],
    "story": "Original Story"
  },
  "Sunglasses": {
    "displayName": "Sunglasses",
    "actions": [
      "Inspect",
      "Take",
      "Use With..."
    ],
    "story": "Original Story"
  },
  "Sweeties": {
    "displayName": "Sweeties",
    "actions": [
      "Inspect",
      "Use With...",
      "Take",
      "Eat"
    ],
    "story": "Original Story"
  },
  "Tablet": {
    "displayName": "Tablet",
    "actions": [
      "Inspect Recipe",
      "Take",
      "FLASHN'DASH"
    ],
    "story": "Date Night With Brittney"
  },
  "Talking Fish": {
    "displayName": "Sleazy Sancho",
    "actions": [
      "Inspect",
      "Use With...",
      "Poke"
    ],
    "story": "Original Story"
  },
  "Tater BGC Handler": {
    "displayName": "Tater",
    "actions": [],
    "story": "Original Story"
  },
  "Tater's Door": {
    "displayName": "Tater's Hill",
    "actions": [
      "Inspect",
      "Knock"
    ],
    "story": "Original Story"
  },
  "Tentacle": {
    "displayName": "Tentacle",
    "actions": [
      "Feed the Kraken",
      "No Thank You, Kraken"
    ],
    "story": "Original Story"
  },
  "Terrarium": {
    "displayName": "Terrarium",
    "actions": [
      "Inspect",
      "Use With...",
      "Latch",
      "Unlatch"
    ],
    "story": "Original Story"
  },
  "Thermos": {
    "displayName": "Thermos",
    "actions": [
      "Inspect",
      "Take",
      "Use With...",
      "Smell"
    ],
    "story": "Original Story"
  },
  "Thermostat": {
    "displayName": "Thermostat",
    "actions": [
      "Inspect",
      "Tamper",
      "Use With..."
    ],
    "story": "Original Story"
  },
  "Toaster": {
    "displayName": "Toaster",
    "actions": [
      "Inspect",
      "Use With..."
    ],
    "story": "Original Story"
  },
  "Towel": {
    "displayName": "Towel",
    "actions": [
      "Inspect",
      "Lift"
    ],
    "story": "Date Night With Brittney"
  },
  "Towel2": {
    "displayName": "Towel",
    "actions": [
      "Inspect",
      "Take",
      "Use With..."
    ],
    "story": "Original Story"
  },
  "Towel3": {
    "displayName": "Towel",
    "actions": [
      "Inspect",
      "Take",
      "Use With..."
    ],
    "story": "Original Story"
  },
  "Trash Can": {
    "displayName": "Trash Can",
    "actions": [
      "Inspect",
      "Use With...",
      "Rummage"
    ],
    "story": "Original Story"
  },
  "Trunk": {
    "displayName": "Trunk",
    "actions": [],
    "story": "Original Story"
  },
  "Trunk Lid": {
    "displayName": "Trunk",
    "actions": [
      "Inspect",
      "Use With..."
    ],
    "story": "Original Story"
  },
  "USB Stick": {
    "displayName": "USB Stick",
    "actions": [
      "Inspect",
      "Take",
      "Use With..."
    ],
    "story": "Original Story"
  },
  "Upstairs Bathroom Door": {
    "displayName": "Upstairs Bathroom Door",
    "actions": [
      "Open",
      "Close",
      "Lock"
    ],
    "story": "A Vickie Vixen Valentine"
  },
  "UpstairsBathroomToilet": {
    "displayName": "Closed Toilet",
    "actions": [
      "Sit"
    ],
    "story": "Original Story"
  },
  "Utility Closet Door": {
    "displayName": "Utility Closet Door",
    "actions": [
      "Open",
      "Close"
    ],
    "story": "A Vickie Vixen Valentine"
  },
  "Valentines Chocolates": {
    "displayName": "Valentine's Chocolates",
    "actions": [
      "Inspect",
      "Take",
      "Use With..."
    ],
    "story": "Original Story"
  },
  "Vanity Chair": {
    "displayName": "Vanity Chair",
    "actions": [
      "Sit"
    ],
    "story": "A Vickie Vixen Valentine"
  },
  "Vibrator": {
    "displayName": "Vibratron 3000",
    "actions": [
      "Inspect",
      "Take",
      "Use With...",
      "Clitpocalypse"
    ],
    "story": "Original Story"
  },
  "Vickie": {
    "displayName": "Vickie",
    "actions": [
      "Talk",
      "Give",
      "Play",
      "Approach",
      "Fuck",
      "Missionary",
      "Doggy",
      "Cowgirl",
      "Eat Out"
    ],
    "story": "A Vickie Vixen Valentine"
  },
  "Vickie's Panties": {
    "displayName": "Vickie's Panties",
    "actions": [
      "Inspect"
    ],
    "story": "A Vickie Vixen Valentine"
  },
  "VickiesPhone": {
    "displayName": "Vickie's Phone",
    "actions": [
      "Inspect",
      "Take",
      "Use With...",
      "Play Podcast"
    ],
    "story": "Original Story"
  },
  "Vintage Condom": {
    "displayName": "Vintage Condom",
    "actions": [
      "Inspect",
      "Take",
      "Use With..."
    ],
    "story": "Original Story"
  },
  "Vodka": {
    "displayName": "Empty Vodka Bottle",
    "actions": [
      "Inspect",
      "Take",
      "Use With...",
      "Drink"
    ],
    "story": "Original Story"
  },
  "VoiceRecorder": {
    "displayName": "Voice Recorder",
    "actions": [
      "Inspect",
      "Use With...",
      "Play",
      "Loop"
    ],
    "story": "Original Story"
  },
  "Washer": {
    "displayName": "Washer",
    "actions": [
      "Inspect",
      "Open",
      "Use With..."
    ],
    "story": "Original Story"
  },
  "WaterMain": {
    "displayName": "Water Main",
    "actions": [
      "Inspect",
      "Turn Off",
      "Turn On"
    ],
    "story": "Original Story"
  },
  "WhalePoster": {
    "displayName": "Whale Poster",
    "actions": [
      "Inspect",
      "Take",
      "Use With..."
    ],
    "story": "Original Story"
  },
  "Whipped Cream": {
    "displayName": "Whipped Cream",
    "actions": [
      "Inspect",
      "Take",
      "Use With...",
      "Hold in Hand"
    ],
    "story": "Original Story"
  },
  "Wrench": {
    "displayName": "Wrench",
    "actions": [
      "Inspect",
      "Take",
      "Use With..."
    ],
    "story": "Original Story"
  }
}